pygeofilter_aeronet/__about__.py
pygeofilter_aeronet/__init__.py
pygeofilter_aeronet/cli.py
pygeofilter_aeronet/evaluator.py
pygeofilter_aeronet/utils.py
pygeofilter_aeronet/aeronet_client/__init__.py
pygeofilter_aeronet/aeronet_client/client.py
pygeofilter_aeronet/aeronet_client/errors.py
pygeofilter_aeronet/aeronet_client/types.py
pygeofilter_aeronet/aeronet_client/api/__init__.py
pygeofilter_aeronet/aeronet_client/api/default/__init__.py
pygeofilter_aeronet/aeronet_client/api/default/get_stations.py
pygeofilter_aeronet/aeronet_client/api/default/search.py
pygeofilter_aeronet/aeronet_client/models/__init__.py
pygeofilter_aeronet/aeronet_client/models/search_avg.py
pygeofilter_aeronet-0.8.0.dist-info/METADATA
pygeofilter_aeronet-0.8.0.dist-info/WHEEL
pygeofilter_aeronet-0.8.0.dist-info/entry_points.txt
pygeofilter_aeronet-0.8.0.dist-info/licenses/LICENSE
pygeofilter_aeronet-0.8.0.dist-info/licenses/NOTICE
pygeofilter_aeronet-0.8.0.dist-info/RECORD
