Metadata-Version: 2.4
Name: pygeofilter-aeronet
Version: 0.8.0
Project-URL: Documentation, https://github.com/Terradue/pygeofilter-aeronet#readme
Project-URL: Issues, https://github.com/Terradue/pygeofilter-aeronet/issues
Project-URL: Source, https://github.com/Terradue/pygeofilter-aeronet
Author-email: Fabrice Brito <fabrice.brito@terradue.com>, Simone Tripodi <simone.tripodi@terradue.com>
License-Expression: Apache-2.0
License-File: LICENSE
License-File: NOTICE
Classifier: Development Status :: 4 - Beta
Classifier: Programming Language :: Python
Classifier: Programming Language :: Python :: 3.9
Classifier: Programming Language :: Python :: 3.10
Classifier: Programming Language :: Python :: 3.11
Classifier: Programming Language :: Python :: 3.12
Classifier: Programming Language :: Python :: Implementation :: CPython
Classifier: Programming Language :: Python :: Implementation :: PyPy
Requires-Python: >=3.8
Requires-Dist: attrs>=22.2.0
Requires-Dist: click>=8.3.0
Requires-Dist: geopandas
Requires-Dist: httpx<0.29.0,>=0.23.0
Requires-Dist: ipykernel
Requires-Dist: loguru
Requires-Dist: nose2
Requires-Dist: pandas>=2.3
Requires-Dist: pyarrow
Requires-Dist: pygeofilter-duckdb
Requires-Dist: pygeofilter>=0.3.1
Requires-Dist: pystac
Requires-Dist: python-dateutil>=2.8.2
Requires-Dist: requests
Requires-Dist: shapely
Requires-Dist: stac-geoparquet
